{
  "ABIRoot": {
    "kind": "Root",
    "name": "TopLevel",
    "printedName": "TopLevel",
    "children": [
      {
        "kind": "Import",
        "name": "Foundation",
        "printedName": "Foundation",
        "declKind": "Import",
        "moduleName": "income_tax_sdk",
        "declAttributes": [
          "RawDocComment"
        ]
      },
      {
        "kind": "Import",
        "name": "Foundation",
        "printedName": "Foundation",
        "declKind": "Import",
        "moduleName": "income_tax_sdk",
        "declAttributes": [
          "RawDocComment"
        ]
      },
      {
        "kind": "Import",
        "name": "SwiftUI",
        "printedName": "SwiftUI",
        "declKind": "Import",
        "moduleName": "income_tax_sdk"
      },
      {
        "kind": "TypeDecl",
        "name": "QuickoSDK",
        "printedName": "QuickoSDK",
        "children": [
          {
            "kind": "Var",
            "name": "instance",
            "printedName": "instance",
            "children": [
              {
                "kind": "TypeNominal",
                "name": "QuickoSDK",
                "printedName": "income_tax_sdk.QuickoSDK",
                "usr": "s:14income_tax_sdk9QuickoSDKC"
              }
            ],
            "declKind": "Var",
            "usr": "s:14income_tax_sdk9QuickoSDKC8instanceACvpZ",
            "mangledName": "$s14income_tax_sdk9QuickoSDKC8instanceACvpZ",
            "moduleName": "income_tax_sdk",
            "static": true,
            "declAttributes": [
              "HasInitialValue",
              "Final",
              "HasStorage",
              "AccessControl"
            ],
            "isLet": true,
            "hasStorage": true,
            "accessors": [
              {
                "kind": "Accessor",
                "name": "Get",
                "printedName": "Get()",
                "children": [
                  {
                    "kind": "TypeNominal",
                    "name": "QuickoSDK",
                    "printedName": "income_tax_sdk.QuickoSDK",
                    "usr": "s:14income_tax_sdk9QuickoSDKC"
                  }
                ],
                "declKind": "Accessor",
                "usr": "s:14income_tax_sdk9QuickoSDKC8instanceACvgZ",
                "mangledName": "$s14income_tax_sdk9QuickoSDKC8instanceACvgZ",
                "moduleName": "income_tax_sdk",
                "static": true,
                "implicit": true,
                "declAttributes": [
                  "Final"
                ],
                "accessorKind": "get"
              }
            ]
          },
          {
            "kind": "Function",
            "name": "setAPIKey",
            "printedName": "setAPIKey(_:)",
            "children": [
              {
                "kind": "TypeNominal",
                "name": "Void",
                "printedName": "()"
              },
              {
                "kind": "TypeNominal",
                "name": "String",
                "printedName": "Swift.String",
                "usr": "s:SS"
              }
            ],
            "declKind": "Func",
            "usr": "s:14income_tax_sdk9QuickoSDKC9setAPIKeyyySSKF",
            "mangledName": "$s14income_tax_sdk9QuickoSDKC9setAPIKeyyySSKF",
            "moduleName": "income_tax_sdk",
            "isOpen": true,
            "declAttributes": [
              "AccessControl",
              "RawDocComment"
            ],
            "throwing": true,
            "funcSelfKind": "NonMutating"
          },
          {
            "kind": "Function",
            "name": "open",
            "printedName": "open(controller:options:)",
            "children": [
              {
                "kind": "TypeNominal",
                "name": "Void",
                "printedName": "()"
              },
              {
                "kind": "TypeNominal",
                "name": "UIViewController",
                "printedName": "UIKit.UIViewController",
                "usr": "c:objc(cs)UIViewController"
              },
              {
                "kind": "TypeNominal",
                "name": "Optional",
                "printedName": "[Swift.String : Any]?",
                "children": [
                  {
                    "kind": "TypeNominal",
                    "name": "Dictionary",
                    "printedName": "[Swift.String : Any]",
                    "children": [
                      {
                        "kind": "TypeNominal",
                        "name": "String",
                        "printedName": "Swift.String",
                        "usr": "s:SS"
                      },
                      {
                        "kind": "TypeNominal",
                        "name": "ProtocolComposition",
                        "printedName": "Any"
                      }
                    ],
                    "usr": "s:SD"
                  }
                ],
                "usr": "s:Sq"
              }
            ],
            "declKind": "Func",
            "usr": "s:14income_tax_sdk9QuickoSDKC4open10controller7optionsySo16UIViewControllerC_SDySSypGSgtYaKF",
            "mangledName": "$s14income_tax_sdk9QuickoSDKC4open10controller7optionsySo16UIViewControllerC_SDySSypGSgtYaKF",
            "moduleName": "income_tax_sdk",
            "isOpen": true,
            "declAttributes": [
              "AccessControl",
              "Custom",
              "RawDocComment"
            ],
            "throwing": true,
            "funcSelfKind": "NonMutating"
          },
          {
            "kind": "Function",
            "name": "setEventListener",
            "printedName": "setEventListener(eventListener:)",
            "children": [
              {
                "kind": "TypeNominal",
                "name": "Void",
                "printedName": "()"
              },
              {
                "kind": "TypeNominal",
                "name": "EventListener",
                "printedName": "any income_tax_sdk.EventListener",
                "usr": "s:14income_tax_sdk13EventListenerP"
              }
            ],
            "declKind": "Func",
            "usr": "s:14income_tax_sdk9QuickoSDKC16setEventListener05eventH0yAA0gH0_p_tF",
            "mangledName": "$s14income_tax_sdk9QuickoSDKC16setEventListener05eventH0yAA0gH0_p_tF",
            "moduleName": "income_tax_sdk",
            "isOpen": true,
            "declAttributes": [
              "AccessControl",
              "RawDocComment"
            ],
            "funcSelfKind": "NonMutating"
          }
        ],
        "declKind": "Class",
        "usr": "s:14income_tax_sdk9QuickoSDKC",
        "mangledName": "$s14income_tax_sdk9QuickoSDKC",
        "moduleName": "income_tax_sdk",
        "isOpen": true,
        "declAttributes": [
          "AccessControl",
          "RawDocComment"
        ],
        "hasMissingDesignatedInitializers": true
      },
      {
        "kind": "Import",
        "name": "SwiftUI",
        "printedName": "SwiftUI",
        "declKind": "Import",
        "moduleName": "income_tax_sdk",
        "declAttributes": [
          "RawDocComment"
        ]
      },
      {
        "kind": "Import",
        "name": "Foundation",
        "printedName": "Foundation",
        "declKind": "Import",
        "moduleName": "income_tax_sdk",
        "declAttributes": [
          "RawDocComment"
        ]
      },
      {
        "kind": "Import",
        "name": "SwiftUI",
        "printedName": "SwiftUI",
        "declKind": "Import",
        "moduleName": "income_tax_sdk"
      },
      {
        "kind": "Import",
        "name": "Foundation",
        "printedName": "Foundation",
        "declKind": "Import",
        "moduleName": "income_tax_sdk",
        "declAttributes": [
          "RawDocComment"
        ]
      },
      {
        "kind": "Import",
        "name": "SwiftUI",
        "printedName": "SwiftUI",
        "declKind": "Import",
        "moduleName": "income_tax_sdk"
      },
      {
        "kind": "Import",
        "name": "Foundation",
        "printedName": "Foundation",
        "declKind": "Import",
        "moduleName": "income_tax_sdk",
        "declAttributes": [
          "RawDocComment"
        ]
      },
      {
        "kind": "Import",
        "name": "Foundation",
        "printedName": "Foundation",
        "declKind": "Import",
        "moduleName": "income_tax_sdk",
        "declAttributes": [
          "RawDocComment"
        ]
      },
      {
        "kind": "Import",
        "name": "SwiftUI",
        "printedName": "SwiftUI",
        "declKind": "Import",
        "moduleName": "income_tax_sdk"
      },
      {
        "kind": "Import",
        "name": "Foundation",
        "printedName": "Foundation",
        "declKind": "Import",
        "moduleName": "income_tax_sdk",
        "declAttributes": [
          "RawDocComment"
        ]
      },
      {
        "kind": "Import",
        "name": "WebKit",
        "printedName": "WebKit",
        "declKind": "Import",
        "moduleName": "income_tax_sdk"
      },
      {
        "kind": "Import",
        "name": "SwiftUI",
        "printedName": "SwiftUI",
        "declKind": "Import",
        "moduleName": "income_tax_sdk"
      },
      {
        "kind": "Import",
        "name": "Foundation",
        "printedName": "Foundation",
        "declKind": "Import",
        "moduleName": "income_tax_sdk"
      },
      {
        "kind": "Import",
        "name": "WebKit",
        "printedName": "WebKit",
        "declKind": "Import",
        "moduleName": "income_tax_sdk"
      },
      {
        "kind": "Import",
        "name": "Foundation",
        "printedName": "Foundation",
        "declKind": "Import",
        "moduleName": "income_tax_sdk",
        "declAttributes": [
          "RawDocComment"
        ]
      },
      {
        "kind": "TypeDecl",
        "name": "EventListener",
        "printedName": "EventListener",
        "children": [
          {
            "kind": "Function",
            "name": "onEvent",
            "printedName": "onEvent(event:)",
            "children": [
              {
                "kind": "TypeNominal",
                "name": "Void",
                "printedName": "()"
              },
              {
                "kind": "TypeNominal",
                "name": "Dictionary",
                "printedName": "[Swift.String : Any]",
                "children": [
                  {
                    "kind": "TypeNominal",
                    "name": "String",
                    "printedName": "Swift.String",
                    "usr": "s:SS"
                  },
                  {
                    "kind": "TypeNominal",
                    "name": "ProtocolComposition",
                    "printedName": "Any"
                  }
                ],
                "usr": "s:SD"
              }
            ],
            "declKind": "Func",
            "usr": "s:14income_tax_sdk13EventListenerP02onD05eventySDySSypG_tF",
            "mangledName": "$s14income_tax_sdk13EventListenerP02onD05eventySDySSypG_tF",
            "moduleName": "income_tax_sdk",
            "genericSig": "<τ_0_0 where τ_0_0 : income_tax_sdk.EventListener>",
            "sugared_genericSig": "<Self where Self : income_tax_sdk.EventListener>",
            "protocolReq": true,
            "declAttributes": [
              "RawDocComment"
            ],
            "reqNewWitnessTableEntry": true,
            "funcSelfKind": "NonMutating"
          }
        ],
        "declKind": "Protocol",
        "usr": "s:14income_tax_sdk13EventListenerP",
        "mangledName": "$s14income_tax_sdk13EventListenerP",
        "moduleName": "income_tax_sdk",
        "declAttributes": [
          "AccessControl",
          "RawDocComment"
        ]
      },
      {
        "kind": "Import",
        "name": "Foundation",
        "printedName": "Foundation",
        "declKind": "Import",
        "moduleName": "income_tax_sdk",
        "declAttributes": [
          "RawDocComment"
        ]
      },
      {
        "kind": "Import",
        "name": "Foundation",
        "printedName": "Foundation",
        "declKind": "Import",
        "moduleName": "income_tax_sdk",
        "declAttributes": [
          "RawDocComment"
        ]
      },
      {
        "kind": "Import",
        "name": "Foundation",
        "printedName": "Foundation",
        "declKind": "Import",
        "moduleName": "income_tax_sdk",
        "declAttributes": [
          "RawDocComment"
        ]
      },
      {
        "kind": "Import",
        "name": "SwiftUI",
        "printedName": "SwiftUI",
        "declKind": "Import",
        "moduleName": "income_tax_sdk"
      },
      {
        "kind": "Import",
        "name": "Foundation",
        "printedName": "Foundation",
        "declKind": "Import",
        "moduleName": "income_tax_sdk",
        "declAttributes": [
          "RawDocComment"
        ]
      },
      {
        "kind": "Import",
        "name": "SwiftUI",
        "printedName": "SwiftUI",
        "declKind": "Import",
        "moduleName": "income_tax_sdk"
      },
      {
        "kind": "Import",
        "name": "Foundation",
        "printedName": "Foundation",
        "declKind": "Import",
        "moduleName": "income_tax_sdk",
        "declAttributes": [
          "RawDocComment"
        ]
      },
      {
        "kind": "Import",
        "name": "SwiftUI",
        "printedName": "SwiftUI",
        "declKind": "Import",
        "moduleName": "income_tax_sdk"
      },
      {
        "kind": "Import",
        "name": "WebKit",
        "printedName": "WebKit",
        "declKind": "Import",
        "moduleName": "income_tax_sdk"
      },
      {
        "kind": "Import",
        "name": "Foundation",
        "printedName": "Foundation",
        "declKind": "Import",
        "moduleName": "income_tax_sdk",
        "declAttributes": [
          "RawDocComment"
        ]
      },
      {
        "kind": "Import",
        "name": "Foundation",
        "printedName": "Foundation",
        "declKind": "Import",
        "moduleName": "income_tax_sdk",
        "declAttributes": [
          "RawDocComment"
        ]
      },
      {
        "kind": "Import",
        "name": "Foundation",
        "printedName": "Foundation",
        "declKind": "Import",
        "moduleName": "income_tax_sdk",
        "declAttributes": [
          "RawDocComment"
        ]
      },
      {
        "kind": "Import",
        "name": "WebKit",
        "printedName": "WebKit",
        "declKind": "Import",
        "moduleName": "income_tax_sdk"
      },
      {
        "kind": "Import",
        "name": "Foundation",
        "printedName": "Foundation",
        "declKind": "Import",
        "moduleName": "income_tax_sdk"
      },
      {
        "kind": "Import",
        "name": "UIKit",
        "printedName": "UIKit",
        "declKind": "Import",
        "moduleName": "income_tax_sdk"
      },
      {
        "kind": "Import",
        "name": "SwiftUI",
        "printedName": "SwiftUI",
        "declKind": "Import",
        "moduleName": "income_tax_sdk"
      },
      {
        "kind": "Import",
        "name": "DeveloperToolsSupport",
        "printedName": "DeveloperToolsSupport",
        "declKind": "Import",
        "moduleName": "income_tax_sdk"
      }
    ],
    "json_format_version": 8
  },
  "ConstValues": [
    {
      "filePath": "\/Users\/nachiketa\/code\/work\/com.quicko.it\/feature-it-fy-24\/common\/ios\/income-tax-sdk\/income-tax-sdk\/lib\/services\/app\/App.service.swift",
      "kind": "StringLiteral",
      "offset": 453,
      "length": 65,
      "value": "\"https:\/\/28yq9t6oe2.execute-api.ap-south-1.amazonaws.com\/dev\/app\""
    },
    {
      "filePath": "\/Users\/nachiketa\/code\/work\/com.quicko.it\/feature-it-fy-24\/common\/ios\/income-tax-sdk\/income-tax-sdk\/lib\/ui\/income-tax-mobile-app\/IncomeTaxMobileAppViewController.swift",
      "kind": "StringLiteral",
      "offset": 157,
      "length": 32,
      "value": "\"income_tax_sdk.IncomeTaxMobileAppViewController\""
    },
    {
      "filePath": "\/Users\/nachiketa\/code\/work\/com.quicko.it\/feature-it-fy-24\/common\/ios\/income-tax-sdk\/income-tax-sdk\/lib\/beans\/api\/APIResponse.swift",
      "kind": "StringLiteral",
      "offset": 458,
      "length": 16,
      "value": "\"transaction_id\""
    },
    {
      "filePath": "\/Users\/nachiketa\/code\/work\/com.quicko.it\/feature-it-fy-24\/common\/ios\/income-tax-sdk\/income-tax-sdk\/lib\/beans\/api\/APIResponse.swift",
      "kind": "StringLiteral",
      "offset": 458,
      "length": 16,
      "value": "\"transaction_id\""
    },
    {
      "filePath": "\/Users\/nachiketa\/code\/work\/com.quicko.it\/feature-it-fy-24\/common\/ios\/income-tax-sdk\/income-tax-sdk\/lib\/beans\/app\/App.swift",
      "kind": "StringLiteral",
      "offset": 489,
      "length": 9,
      "value": "\"@entity\""
    },
    {
      "filePath": "\/Users\/nachiketa\/code\/work\/com.quicko.it\/feature-it-fy-24\/common\/ios\/income-tax-sdk\/income-tax-sdk\/lib\/beans\/app\/App.swift",
      "kind": "StringLiteral",
      "offset": 557,
      "length": 10,
      "value": "\"app_name\""
    },
    {
      "filePath": "\/Users\/nachiketa\/code\/work\/com.quicko.it\/feature-it-fy-24\/common\/ios\/income-tax-sdk\/income-tax-sdk\/lib\/beans\/app\/App.swift",
      "kind": "StringLiteral",
      "offset": 590,
      "length": 9,
      "value": "\"app_key\""
    },
    {
      "filePath": "\/Users\/nachiketa\/code\/work\/com.quicko.it\/feature-it-fy-24\/common\/ios\/income-tax-sdk\/income-tax-sdk\/lib\/beans\/app\/App.swift",
      "kind": "StringLiteral",
      "offset": 489,
      "length": 9,
      "value": "\"@entity\""
    },
    {
      "filePath": "\/Users\/nachiketa\/code\/work\/com.quicko.it\/feature-it-fy-24\/common\/ios\/income-tax-sdk\/income-tax-sdk\/lib\/beans\/app\/App.swift",
      "kind": "StringLiteral",
      "offset": 557,
      "length": 10,
      "value": "\"app_name\""
    },
    {
      "filePath": "\/Users\/nachiketa\/code\/work\/com.quicko.it\/feature-it-fy-24\/common\/ios\/income-tax-sdk\/income-tax-sdk\/lib\/beans\/app\/App.swift",
      "kind": "StringLiteral",
      "offset": 590,
      "length": 9,
      "value": "\"app_key\""
    },
    {
      "filePath": "\/Users\/nachiketa\/code\/work\/com.quicko.it\/feature-it-fy-24\/common\/ios\/income-tax-sdk\/income-tax-sdk\/lib\/ui\/widgets\/ContentView.swift",
      "kind": "BooleanLiteral",
      "offset": 193,
      "length": 4,
      "value": "true"
    },
    {
      "filePath": "\/Users\/nachiketa\/code\/work\/com.quicko.it\/feature-it-fy-24\/common\/ios\/income-tax-sdk\/income-tax-sdk\/lib\/ui\/widgets\/IncomeTaxWebView.swift",
      "kind": "StringLiteral",
      "offset": 1373,
      "length": 11,
      "value": "\"income_tax_sdk.Coordinator\""
    },
    {
      "filePath": "\/Users\/nachiketa\/code\/work\/com.quicko.it\/feature-it-fy-24\/common\/ios\/income-tax-sdk\/income-tax-sdk\/lib\/services\/splash\/SplashContent.service.swift",
      "kind": "StringLiteral",
      "offset": 511,
      "length": 73,
      "value": "\"https:\/\/d12ldzklkk1lqk.cloudfront.net\/api\/com-quicko-connect-sdk-splash\""
    },
    {
      "filePath": "\/Users\/nachiketa\/code\/work\/com.quicko.it\/feature-it-fy-24\/common\/ios\/income-tax-sdk\/income-tax-sdk\/lib\/beans\/splash\/SplashContent.swift",
      "kind": "StringLiteral",
      "offset": 346,
      "length": 26,
      "value": "\"terms_and_conditions_url\""
    },
    {
      "filePath": "\/Users\/nachiketa\/code\/work\/com.quicko.it\/feature-it-fy-24\/common\/ios\/income-tax-sdk\/income-tax-sdk\/lib\/beans\/splash\/SplashContent.swift",
      "kind": "StringLiteral",
      "offset": 405,
      "length": 20,
      "value": "\"privacy_policy_url\""
    },
    {
      "filePath": "\/Users\/nachiketa\/code\/work\/com.quicko.it\/feature-it-fy-24\/common\/ios\/income-tax-sdk\/income-tax-sdk\/lib\/beans\/splash\/SplashContent.swift",
      "kind": "StringLiteral",
      "offset": 346,
      "length": 26,
      "value": "\"terms_and_conditions_url\""
    },
    {
      "filePath": "\/Users\/nachiketa\/code\/work\/com.quicko.it\/feature-it-fy-24\/common\/ios\/income-tax-sdk\/income-tax-sdk\/lib\/beans\/splash\/SplashContent.swift",
      "kind": "StringLiteral",
      "offset": 405,
      "length": 20,
      "value": "\"privacy_policy_url\""
    },
    {
      "filePath": "\/Users\/nachiketa\/Library\/Developer\/Xcode\/DerivedData\/income-tax-sdk-bwiemjnchekoupfkkeklzjnwyjvj\/Build\/Intermediates.noindex\/ArchiveIntermediates\/income-tax-sdk\/IntermediateBuildFilesPath\/income-tax-sdk.build\/Release-iphonesimulator\/income-tax-sdk.build\/DerivedSources\/GeneratedAssetSymbols.swift",
      "kind": "StringLiteral",
      "offset": 818,
      "length": 8,
      "value": "\"quicko\""
    }
  ]
}